{
  "kind": "youtube#channelListResponse",
  "etag": "3qie-o_y285QbfAE4dQOGmEbFTY",
  "pageInfo": {
    "totalResults": 1,
    "resultsPerPage": 5
  },
  "items": [
    {
      "id": "IT1",
      "rank": 0,
      "snippet": {
        "title": "Unbox Therapy",
        "thumbnails": {
          "default": {
            "url": "https://yt3.ggpht.com/ytc/AAUvwnh3QH3UYxKLoz4S9dRE9dDo_nhqE6cUZYASHYTJQQ=s240-c-k-c0x00ffffff-no-rj",
            "width": 88,
            "height": 88
          },
          "medium": {
            "url": "https://yt3.ggpht.com/ytc/AAUvwnh3QH3UYxKLoz4S9dRE9dDo_nhqE6cUZYASHYTJQQ=s240-c-k-c0x00ffffff-no-rj",
            "width": 240,
            "height": 240
          },
          "high": {
            "url": "https://yt3.ggpht.com/ytc/AAUvwnh3QH3UYxKLoz4S9dRE9dDo_nhqE6cUZYASHYTJQQ=s240-c-k-c0x00ffffff-no-rj",
            "width": 800,
            "height": 800
          }
        },
        "localized": {
          "title": "Unbox Therapy"
        }
      },
      "statistics": {
        "subscriberCount": "17500000"
      }
    },

    {
      "id": "IT2",
      "rank": 1,
      "snippet": {
        "title": "Apple",
        "thumbnails": {
          "default": {
            "url": "https://yt3.ggpht.com/a/AATXAJzLJovKyZ7JLdndJ5foqqFL-Xt8Zm28UtEuFRW2Gg=s240-c-k-c0x00ffffff-no-rj",
            "width": 88,
            "height": 88
          },
          "medium": {
            "url": "https://yt3.ggpht.com/a/AATXAJzLJovKyZ7JLdndJ5foqqFL-Xt8Zm28UtEuFRW2Gg=s240-c-k-c0x00ffffff-no-rj",
            "width": 240,
            "height": 240
          },
          "high": {
            "url": "https://yt3.ggpht.com/a/AATXAJzLJovKyZ7JLdndJ5foqqFL-Xt8Zm28UtEuFRW2Gg=s240-c-k-c0x00ffffff-no-rj",
            "width": 800,
            "height": 800
          }
        },
        "localized": {
          "title": "Apple"
        }
      },
      "statistics": {
        "subscriberCount": "13600000"
      }
    },

    {
      "id": "IT3",
      "rank": 2,
      "snippet": {
        "title": "Marques Brownlee",
        "thumbnails": {
          "default": {
            "url": "https://yt3.ggpht.com/ytc/AAUvwnhoa6jtz7ccGj30Al2Ha8t4ImDVW2U98STxoLXp=s240-c-k-c0x00ffffff-no-rj",
            "width": 88,
            "height": 88
          },
          "medium": {
            "url": "https://yt3.ggpht.com/ytc/AAUvwnhoa6jtz7ccGj30Al2Ha8t4ImDVW2U98STxoLXp=s240-c-k-c0x00ffffff-no-rj",
            "width": 240,
            "height": 240
          },
          "high": {
            "url": "https://yt3.ggpht.com/ytc/AAUvwnhoa6jtz7ccGj30Al2Ha8t4ImDVW2U98STxoLXp=s240-c-k-c0x00ffffff-no-rj",
            "width": 800,
            "height": 800
          }
        },
        "localized": {
          "title": "Marques Brownlee"
        }
      },
      "statistics": {
        "subscriberCount": "12900000"
      }
    },

    {
      "id": "IT4",
      "rank": 3,
      "snippet": {
        "title": "Primitive Technology",
        "thumbnails": {
          "default": {
            "url": "https://yt3.ggpht.com/a/AATXAJyonU4tQHsT5M8L-yW4xjkVR4GdKZNpQztT4CtI=s240-c-k-c0x00ffffff-no-rj",
            "width": 88,
            "height": 88
          },
          "medium": {
            "url": "https://yt3.ggpht.com/a/AATXAJyonU4tQHsT5M8L-yW4xjkVR4GdKZNpQztT4CtI=s240-c-k-c0x00ffffff-no-rj",
            "width": 240,
            "height": 240
          },
          "high": {
            "url": "https://yt3.ggpht.com/a/AATXAJyonU4tQHsT5M8L-yW4xjkVR4GdKZNpQztT4CtI=s240-c-k-c0x00ffffff-no-rj",
            "width": 800,
            "height": 800
          }
        },
        "localized": {
          "title": "Primitive Technology"
        }
      },
      "statistics": {
        "subscriberCount": "10300000"
      }
    },

    {
      "id": "IT5",
      "rank": 4,
      "snippet": {
        "title": "Wylsacom",
        "thumbnails": {
          "default": {
            "url": "https://yt3.ggpht.com/a/AATXAJzbMD77TmZutaBuQe4F3vDWA1cdZlY4zZ0pa8LYEQ=s240-c-k-c0x00ffffff-no-rj",
            "width": 88,
            "height": 88
          },
          "medium": {
            "url": "https://yt3.ggpht.com/a/AATXAJzbMD77TmZutaBuQe4F3vDWA1cdZlY4zZ0pa8LYEQ=s240-c-k-c0x00ffffff-no-rj",
            "width": 240,
            "height": 240
          },
          "high": {
            "url": "https://yt3.ggpht.com/a/AATXAJzbMD77TmZutaBuQe4F3vDWA1cdZlY4zZ0pa8LYEQ=s240-c-k-c0x00ffffff-no-rj",
            "width": 800,
            "height": 800
          }
        },
        "localized": {
          "title": "Wylsacom"
        }
      },
      "statistics": {
        "subscriberCount": "9700000"
      }
    },

    {
      "id": "IT6",
      "rank": 5,
      "snippet": {
        "title": "Google",
        "thumbnails": {
          "default": {
            "url": "https://yt3.ggpht.com/a/AATXAJysEynEghsvVEHdcjVYfdaDfrimWMiTvtuEVKYTGJM=s240-c-k-c0x00ffffff-no-rj",
            "width": 88,
            "height": 88
          },
          "medium": {
            "url": "https://yt3.ggpht.com/a/AATXAJysEynEghsvVEHdcjVYfdaDfrimWMiTvtuEVKYTGJM=s240-c-k-c0x00ffffff-no-rj",
            "width": 240,
            "height": 240
          },
          "high": {
            "url": "https://yt3.ggpht.com/a/AATXAJysEynEghsvVEHdcjVYfdaDfrimWMiTvtuEVKYTGJM=s240-c-k-c0x00ffffff-no-rj",
            "width": 800,
            "height": 800
          }
        },
        "localized": {
          "title": "Google"
        }
      },
      "statistics": {
        "subscriberCount": "9500000"
      }
    },

    {
      "id": "IT7",
      "rank": 6,
      "snippet": {
        "title": "EverythingApplePro EAP",
        "thumbnails": {
          "default": {
            "url": "https://yt3.ggpht.com/a/AATXAJwfqCFpplCVBfC24odA3fNna-Zt9eG0Bv3LODRknQ=s240-c-k-c0x00ffffff-no-rj",
            "width": 88,
            "height": 88
          },
          "medium": {
            "url": "https://yt3.ggpht.com/a/AATXAJwfqCFpplCVBfC24odA3fNna-Zt9eG0Bv3LODRknQ=s240-c-k-c0x00ffffff-no-rj",
            "width": 240,
            "height": 240
          },
          "high": {
            "url": "https://yt3.ggpht.com/a/AATXAJwfqCFpplCVBfC24odA3fNna-Zt9eG0Bv3LODRknQ=s240-c-k-c0x00ffffff-no-rj",
            "width": 800,
            "height": 800
          }
        },
        "localized": {
          "title": "EverythingApplePro EAP"
        }
      },
      "statistics": {
        "subscriberCount": "8400000"
      }
    },

    {
      "id": "IT8",
      "rank": 7,
      "snippet": {
        "title": "NASA",
        "thumbnails": {
          "default": {
            "url": "https://yt3.ggpht.com/a/AATXAJyjhPLjpkZ54OWzkeD3n6AwZNZE-AigHF_d7PU_kb0=s240-c-k-c0x00ffffff-no-rj",
            "width": 88,
            "height": 88
          },
          "medium": {
            "url": "https://yt3.ggpht.com/a/AATXAJyjhPLjpkZ54OWzkeD3n6AwZNZE-AigHF_d7PU_kb0=s240-c-k-c0x00ffffff-no-rj",
            "width": 240,
            "height": 240
          },
          "high": {
            "url": "https://yt3.ggpht.com/a/AATXAJyjhPLjpkZ54OWzkeD3n6AwZNZE-AigHF_d7PU_kb0=s240-c-k-c0x00ffffff-no-rj",
            "width": 800,
            "height": 800
          }
        },
        "localized": {
          "title": "NASA"
        }
      },
      "statistics": {
        "subscriberCount": "7600000"
      }
    },

    {
      "id": "IT9",
      "rank": 8,
      "snippet": {
        "title": "TAE",
        "thumbnails": {
          "default": {
            "url": "https://yt3.ggpht.com/a/AATXAJzTvSk1o_K6LeeSbh9imzd_u0LCYP4jBUJ-sRhlTQ=s240-c-k-c0x00ffffff-no-rj",
            "width": 88,
            "height": 88
          },
          "medium": {
            "url": "https://yt3.ggpht.com/a/AATXAJzTvSk1o_K6LeeSbh9imzd_u0LCYP4jBUJ-sRhlTQ=s240-c-k-c0x00ffffff-no-rj",
            "width": 240,
            "height": 240
          },
          "high": {
            "url": "https://yt3.ggpht.com/a/AATXAJzTvSk1o_K6LeeSbh9imzd_u0LCYP4jBUJ-sRhlTQ=s240-c-k-c0x00ffffff-no-rj",
            "width": 800,
            "height": 800
          }
        },
        "localized": {
          "title": "TAE"
        }
      },
      "statistics": {
        "subscriberCount": "6700000"
      }
    },

    {
      "id": "IT10",
      "rank": 9,
      "snippet": {
        "title": "GadgetIn",
        "thumbnails": {
          "default": {
            "url": "https://yt3.ggpht.com/a/AATXAJxuWVX6Ko1YxfIcxMDXQaFBULyAxC5kITJx_qyJ=s240-c-k-c0x00ffffff-no-rj",
            "width": 88,
            "height": 88
          },
          "medium": {
            "url": "https://yt3.ggpht.com/a/AATXAJxuWVX6Ko1YxfIcxMDXQaFBULyAxC5kITJx_qyJ=s240-c-k-c0x00ffffff-no-rj",
            "width": 240,
            "height": 240
          },
          "high": {
            "url": "https://yt3.ggpht.com/a/AATXAJxuWVX6Ko1YxfIcxMDXQaFBULyAxC5kITJx_qyJ=s240-c-k-c0x00ffffff-no-rj",
            "width": 800,
            "height": 800
          }
        },
        "localized": {
          "title": "GadgetIn"
        }
      },
      "statistics": {
        "subscriberCount": "6300000"
      }
    }
  ]
}